[{"reflabel":"Definition","title":"","refnum":"??","cls":"Definition","label":"Definition","id":"Definition*-3.1","file":"lecture_7","autoid":"Definition*-3.1","reftag":"","neu":true},{"reflabel":"Definition","title":"","refnum":"??","cls":"Definition","label":"Definition","id":"Definition*-3.2","file":"lecture_7","autoid":"Definition*-3.2","reftag":"","neu":true},{"reflabel":"Theorem","title":"","file":"lecture_7","refnum":"??","id":"Theorem*-3.3","cls":"Theorem","autoid":"Theorem*-3.3","label":"Theorem","reftag":"","neu":true},{"reflabel":"Definition","title":"","refnum":"??","cls":"Definition","label":"Definition","id":"Definition*-3.3","file":"lecture_7","autoid":"Definition*-3.3","reftag":"","neu":true},{"reflabel":"Theorem","title":"","refnum":"??","cls":"Theorem","label":"Theorem","id":"Theorem*-3.4","file":"lecture_7","autoid":"Theorem*-3.4","reftag":"","neu":true},{"reflabel":"Problem","title":"","file":"lecture_7","refnum":"??","id":"Problem*-5.1","cls":"Problem","autoid":"Problem*-5.1","label":"Problem","reftag":"","neu":true},{"reflabel":"Definition","title":"","refnum":"??","cls":"Definition","label":"Definition","id":"Definition*-6.1","file":"lecture_7","autoid":"Definition*-6.1","reftag":"","neu":true},{"reflabel":"Theorem","title":"","refnum":"??","cls":"Theorem","label":"Theorem","id":"Theorem*-6.2","file":"lecture_7","autoid":"Theorem*-6.2","reftag":"","neu":true},{"reflabel":"Theorem","title":"","file":"lecture_7","refnum":"??","id":"Theorem*-7.1","cls":"Theorem","autoid":"Theorem*-7.1","label":"Theorem","reftag":"","neu":true}]