[{"neu":true,"autoid":"Definition*-2.1","file":"lecture_3","title":"","refnum":"??","id":"Definition*-2.1","reftag":"","reflabel":"Definition","cls":"Definition","label":"Definition"},{"neu":true,"autoid":"Definition*-2.2","file":"lecture_3","title":"","refnum":"??","id":"Definition*-2.2","reftag":"","reflabel":"Definition","cls":"Definition","label":"Definition"},{"neu":true,"autoid":"Definition*-2.3","file":"lecture_3","title":"","refnum":"??","id":"Definition*-2.3","reftag":"","reflabel":"Definition","cls":"Definition","label":"Definition"},{"neu":true,"autoid":"Definition*-3.1","file":"lecture_3","title":"","refnum":"??","id":"Definition*-3.1","reftag":"","reflabel":"Definition","cls":"Definition","label":"Definition"},{"neu":true,"autoid":"Definition*-3.2","file":"lecture_3","title":"","refnum":"??","id":"Definition*-3.2","reftag":"","reflabel":"Definition","cls":"Definition","label":"Definition"},{"neu":true,"autoid":"Problem*-3.3","file":"lecture_3","title":"","refnum":"??","id":"Problem*-3.3","reftag":"","reflabel":"Problem","cls":"Problem","label":"Problem"},{"neu":true,"autoid":"Definition*-3.4","file":"lecture_3","title":"","refnum":"??","id":"Definition*-3.4","reftag":"","reflabel":"Definition","cls":"Definition","label":"Definition"},{"neu":true,"autoid":"Theorem*-3.5","file":"lecture_3","title":"","refnum":"??","id":"Theorem*-3.5","reftag":"","reflabel":"Theorem","cls":"Theorem","label":"Theorem"},{"neu":true,"autoid":"Lemma*-3.6","file":"lecture_3","title":"","refnum":"??","id":"Lemma*-3.6","reftag":"","reflabel":"Lemma","cls":"Lemma","label":"Lemma"},{"neu":true,"autoid":"Problem*-3.7","file":"lecture_3","title":"","refnum":"??","id":"Problem*-3.7","reftag":"","reflabel":"Problem","cls":"Problem","label":"Problem"},{"neu":true,"autoid":"Definition*-3.8","file":"lecture_3","title":"","refnum":"??","id":"Definition*-3.8","reftag":"","reflabel":"Definition","cls":"Definition","label":"Definition"},{"neu":true,"autoid":"Proposition*-3.9","file":"lecture_3","title":"","refnum":"??","id":"Proposition*-3.9","reftag":"","reflabel":"Proposition","cls":"Proposition","label":"Proposition"},{"neu":true,"autoid":"Theorem*-3.10","file":"lecture_3","title":"","refnum":"??","id":"Theorem*-3.10","reftag":"","reflabel":"Theorem","cls":"Theorem","label":"Theorem"},{"neu":true,"autoid":"Definition*-4.1","file":"lecture_3","title":"","refnum":"??","id":"Definition*-4.1","reftag":"","reflabel":"Definition","cls":"Definition","label":"Definition"},{"neu":true,"autoid":"Theorem*-4.2","file":"lecture_3","title":"","refnum":"??","id":"Theorem*-4.2","reftag":"","reflabel":"Theorem","cls":"Theorem","label":"Theorem"},{"neu":true,"autoid":"Question*-5.1","file":"lecture_3","title":"","refnum":"??","id":"Question*-5.1","reftag":"","reflabel":"Question","cls":"Question","label":"Question"},{"neu":true,"autoid":"Theorem*-5.2","file":"lecture_3","title":"","refnum":"??","id":"Theorem*-5.2","reftag":"","reflabel":"Theorem","cls":"Theorem","label":"Theorem"},{"neu":true,"autoid":"Lemma*-5.3","file":"lecture_3","title":"","refnum":"??","id":"Lemma*-5.3","reftag":"","reflabel":"Lemma","cls":"Lemma","label":"Lemma"},{"neu":true,"autoid":"Problem*-6.1","file":"lecture_3","title":"","refnum":"??","id":"Problem*-6.1","reftag":"","reflabel":"Problem","cls":"Problem","label":"Problem"},{"neu":true,"autoid":"Question*-6.2","file":"lecture_3","title":"","refnum":"??","id":"Question*-6.2","reftag":"","reflabel":"Question","cls":"Question","label":"Question"},{"neu":true,"autoid":"Question*-6.3","file":"lecture_3","title":"","refnum":"??","id":"Question*-6.3","reftag":"","reflabel":"Question","cls":"Question","label":"Question"},{"neu":true,"autoid":"Important*-6.4","file":"lecture_3","title":"","refnum":"??","id":"Important*-6.4","reftag":"","reflabel":"Important","cls":"Important","label":"Important"},{"neu":true,"autoid":"Problem*-6.5","file":"lecture_3","title":"","refnum":"??","id":"Problem*-6.5","reftag":"","reflabel":"Problem","cls":"Problem","label":"Problem"},{"neu":true,"autoid":"Question*-6.6","file":"lecture_3","title":"","refnum":"??","id":"Question*-6.6","reftag":"","reflabel":"Question","cls":"Question","label":"Question"},{"neu":true,"autoid":"Definition*-6.7","file":"lecture_3","title":"","refnum":"??","id":"Definition*-6.7","reftag":"","reflabel":"Definition","cls":"Definition","label":"Definition"},{"neu":true,"autoid":"Theorem*-6.8","file":"lecture_3","title":"","refnum":"??","id":"Theorem*-6.8","reftag":"","reflabel":"Theorem","cls":"Theorem","label":"Theorem"},{"neu":true,"autoid":"Theorem*-6.9","file":"lecture_3","title":"","refnum":"??","id":"Theorem*-6.9","reftag":"","reflabel":"Theorem","cls":"Theorem","label":"Theorem"},{"neu":true,"autoid":"Proposition*-6.10","file":"lecture_3","title":"Expectation and Variance of t-distribution","refnum":"??","id":"expectation-and-variance-of-t-distribution","reftag":"","reflabel":"Proposition","cls":"Proposition","label":"Proposition"},{"neu":true,"autoid":"Definition*-7.1","file":"lecture_3","title":"","refnum":"??","id":"Definition*-7.1","reftag":"","reflabel":"Definition","cls":"Definition","label":"Definition"},{"neu":true,"autoid":"Definition*-7.2","file":"lecture_3","title":"","refnum":"??","id":"Definition*-7.2","reftag":"","reflabel":"Definition","cls":"Definition","label":"Definition"}]