[{"neu":true,"refnum":"??","label":"Problem","reflabel":"Problem","reftag":"","id":"Problem*-2.1","cls":"Problem","file":"lecture_10","title":"","autoid":"Problem*-2.1"},{"neu":true,"refnum":"??","label":"Definition","id":"Definition*-2.2","cls":"Definition","reftag":"","reflabel":"Definition","file":"lecture_10","title":"","autoid":"Definition*-2.2"},{"neu":true,"refnum":"??","label":"Theorem","reflabel":"Theorem","reftag":"","id":"Theorem*-2.2","cls":"Theorem","file":"lecture_10","title":"","autoid":"Theorem*-2.2"},{"neu":true,"refnum":"??","label":"Proposition","reflabel":"Proposition","reftag":"","id":"Proposition*-2.3","cls":"Proposition","file":"lecture_10","title":"","autoid":"Proposition*-2.3"}]