[{"title":"","id":"Definition*-2.1","label":"Definition","reflabel":"Definition","refnum":"??","cls":"Definition","file":"lecture_9","reftag":"","autoid":"Definition*-2.1","neu":true},{"title":"","id":"Idea*-2.2","label":"Idea","reflabel":"Idea","refnum":"??","cls":"Idea","file":"lecture_9","reftag":"","autoid":"Idea*-2.2","neu":true},{"title":"","id":"Problem*-2.3","label":"Problem","reflabel":"Problem","refnum":"??","cls":"Problem","file":"lecture_9","reftag":"","autoid":"Problem*-2.3","neu":true},{"title":"","id":"Definition*-2.4","label":"Definition","reflabel":"Definition","refnum":"??","cls":"Definition","file":"lecture_9","reftag":"","autoid":"Definition*-2.4","neu":true},{"title":"","id":"Definition*-2.5","label":"Definition","reflabel":"Definition","refnum":"??","cls":"Definition","file":"lecture_9","reftag":"","autoid":"Definition*-2.5","neu":true},{"title":"","id":"Proposition*-2.6","label":"Proposition","reflabel":"Proposition","refnum":"??","cls":"Proposition","file":"lecture_9","reftag":"","autoid":"Proposition*-2.6","neu":true},{"title":"","id":"Proposition*-2.7","label":"Proposition","reflabel":"Proposition","refnum":"??","cls":"Proposition","file":"lecture_9","reftag":"","autoid":"Proposition*-2.7","neu":true},{"title":"","id":"Definition*-2.8","label":"Definition","reflabel":"Definition","refnum":"??","cls":"Definition","file":"lecture_9","reftag":"","autoid":"Definition*-2.8","neu":true},{"title":"","id":"Definition*-2.9","label":"Definition","reflabel":"Definition","refnum":"??","cls":"Definition","file":"lecture_9","reftag":"","autoid":"Definition*-2.9","neu":true},{"title":"","id":"Problem*-2.10","label":"Problem","reflabel":"Problem","refnum":"??","cls":"Problem","file":"lecture_9","reftag":"","autoid":"Problem*-2.10","neu":true},{"title":"","id":"Question*-2.11","label":"Question","reflabel":"Question","refnum":"??","cls":"Question","file":"lecture_9","reftag":"","autoid":"Question*-2.11","neu":true},{"title":"","id":"Theorem*-2.12","label":"Theorem","reflabel":"Theorem","refnum":"??","cls":"Theorem","file":"lecture_9","reftag":"","autoid":"Theorem*-2.12","neu":true},{"title":"","id":"Lemma*-2.13","label":"Lemma","reflabel":"Lemma","refnum":"??","cls":"Lemma","file":"lecture_9","reftag":"","autoid":"Lemma*-2.13","neu":true},{"title":"","id":"Lemma*-2.14","label":"Lemma","reflabel":"Lemma","refnum":"??","cls":"Lemma","file":"lecture_9","reftag":"","autoid":"Lemma*-2.14","neu":true},{"title":"","id":"Theorem*-2.15","label":"Theorem","reflabel":"Theorem","refnum":"??","cls":"Theorem","file":"lecture_9","reftag":"","autoid":"Theorem*-2.15","neu":true},{"title":"","id":"Definition*-5.1","cls":"Definition","refnum":"??","label":"Definition","reflabel":"Definition","file":"lecture_9","reftag":"","autoid":"Definition*-5.1","neu":true},{"title":"","id":"Definition*-5.2","cls":"Definition","refnum":"??","label":"Definition","reflabel":"Definition","file":"lecture_9","reftag":"","autoid":"Definition*-5.2","neu":true},{"title":"","id":"Problem*-5.3","cls":"Problem","refnum":"??","label":"Problem","reflabel":"Problem","file":"lecture_9","reftag":"","autoid":"Problem*-5.3","neu":true},{"title":"","id":"Question*-5.4","cls":"Question","refnum":"??","label":"Question","reflabel":"Question","file":"lecture_9","reftag":"","autoid":"Question*-5.4","neu":true},{"title":"","id":"Definition*-4.1","label":"Definition","reflabel":"Definition","refnum":"??","cls":"Definition","file":"lecture_9","reftag":"","autoid":"Definition*-4.1","neu":true},{"title":"","id":"Definition*-4.2","cls":"Definition","refnum":"??","label":"Definition","reflabel":"Definition","file":"lecture_9","reftag":"","autoid":"Definition*-4.2","neu":true},{"title":"","id":"Problem*-4.3","cls":"Problem","refnum":"??","label":"Problem","reflabel":"Problem","file":"lecture_9","reftag":"","autoid":"Problem*-4.3","neu":true},{"title":"","id":"Question*-4.4","cls":"Question","refnum":"??","label":"Question","reflabel":"Question","file":"lecture_9","reftag":"","autoid":"Question*-4.4","neu":true},{"title":"","id":"Definition*-4.3","cls":"Definition","refnum":"??","label":"Definition","reflabel":"Definition","file":"lecture_9","reftag":"","autoid":"Definition*-4.3","neu":true},{"title":"","id":"Problem*-4.4","cls":"Problem","refnum":"??","label":"Problem","reflabel":"Problem","file":"lecture_9","reftag":"","autoid":"Problem*-4.4","neu":true},{"title":"","id":"Question*-4.5","cls":"Question","refnum":"??","label":"Question","reflabel":"Question","file":"lecture_9","reftag":"","autoid":"Question*-4.5","neu":true}]