[{"cls":"Problem","refnum":"??","title":"","file":"lecture_10","id":"Problem*-2.1","reftag":"","reflabel":"Problem","autoid":"Problem*-2.1","neu":true,"label":"Problem"},{"cls":"Definition","refnum":"??","title":"","file":"lecture_10","id":"Definition*-2.2","reftag":"","reflabel":"Definition","autoid":"Definition*-2.2","neu":true,"label":"Definition"},{"cls":"Theorem","refnum":"??","title":"","file":"lecture_10","id":"Theorem*-2.2","reftag":"","reflabel":"Theorem","autoid":"Theorem*-2.2","neu":true,"label":"Theorem"},{"cls":"Proposition","refnum":"??","title":"","file":"lecture_10","id":"Proposition*-2.3","reftag":"","reflabel":"Proposition","autoid":"Proposition*-2.3","neu":true,"label":"Proposition"},{"cls":"Important","refnum":"??","title":"","neu":true,"id":"Important*-3.1","reftag":"","label":"Important","reflabel":"Important","autoid":"Important*-3.1","file":"lecture_10"},{"cls":"Warning","refnum":"??","title":"","neu":true,"id":"Warning*-3.2","reftag":"","label":"Warning","reflabel":"Warning","autoid":"Warning*-3.2","file":"lecture_10"},{"cls":"Important","refnum":"??","title":"","neu":true,"id":"Important*-3.3","reftag":"","label":"Important","reflabel":"Important","autoid":"Important*-3.3","file":"lecture_10"},{"cls":"Important","refnum":"??","title":"","file":"lecture_10","id":"Important*-3.4","reftag":"","reflabel":"Important","autoid":"Important*-3.4","neu":true,"label":"Important"},{"cls":"Important","refnum":"??","title":"","file":"lecture_10","id":"Important*-3.5","reftag":"","reflabel":"Important","autoid":"Important*-3.5","neu":true,"label":"Important"},{"cls":"Important","refnum":"??","title":"","file":"lecture_10","id":"Important*-2.1","reftag":"","reflabel":"Important","autoid":"Important*-2.1","neu":true,"label":"Important"},{"cls":"Warning","refnum":"??","title":"","file":"lecture_10","id":"Warning*-2.2","reftag":"","reflabel":"Warning","autoid":"Warning*-2.2","neu":true,"label":"Warning"},{"cls":"Important","refnum":"??","title":"","file":"lecture_10","id":"Important*-2.3","reftag":"","reflabel":"Important","autoid":"Important*-2.3","neu":true,"label":"Important"},{"cls":"Theorem","refnum":"??","title":"","neu":true,"id":"Theorem*-4.1","reftag":"","label":"Theorem","reflabel":"Theorem","autoid":"Theorem*-4.1","file":"lecture_10"},{"cls":"Theorem","refnum":"??","title":"","neu":true,"id":"Theorem*-4.2","reftag":"","label":"Theorem","reflabel":"Theorem","autoid":"Theorem*-4.2","file":"lecture_10"},{"cls":"Important","refnum":"??","title":"","file":"lecture_10","id":"Important*-4.1","reftag":"","reflabel":"Important","autoid":"Important*-4.1","neu":true,"label":"Important"},{"cls":"Warning","refnum":"??","title":"","file":"lecture_10","id":"Warning*-4.2","reftag":"","reflabel":"Warning","autoid":"Warning*-4.2","neu":true,"label":"Warning"},{"cls":"Important","refnum":"??","title":"","file":"lecture_10","id":"Important*-4.3","reftag":"","reflabel":"Important","autoid":"Important*-4.3","neu":true,"label":"Important"},{"cls":"Theorem","refnum":"??","title":"","file":"lecture_10","id":"Theorem*-5.1","reftag":"","reflabel":"Theorem","autoid":"Theorem*-5.1","neu":true,"label":"Theorem"},{"cls":"Theorem","refnum":"??","title":"","file":"lecture_10","id":"Theorem*-5.2","reftag":"","reflabel":"Theorem","autoid":"Theorem*-5.2","neu":true,"label":"Theorem"},{"cls":"Theorem","refnum":"??","title":"","file":"lecture_10","id":"Theorem*-5.3","reftag":"","reflabel":"Theorem","autoid":"Theorem*-5.3","neu":true,"label":"Theorem"},{"cls":"Definition","refnum":"??","title":"","file":"lecture_10","id":"Definition*-6.1","reftag":"","reflabel":"Definition","autoid":"Definition*-6.1","neu":true,"label":"Definition"},{"cls":"Theorem","refnum":"??","title":"","file":"lecture_10","id":"Theorem*-6.2","reftag":"","reflabel":"Theorem","autoid":"Theorem*-6.2","neu":true,"label":"Theorem"},{"cls":"Proposition","refnum":"??","title":"","file":"lecture_10","id":"Proposition*-6.2","reftag":"","reflabel":"Proposition","autoid":"Proposition*-6.2","neu":true,"label":"Proposition"},{"cls":"Proposition","refnum":"??","title":"","file":"lecture_10","id":"Proposition*-6.3","reftag":"","reflabel":"Proposition","autoid":"Proposition*-6.3","neu":true,"label":"Proposition"},{"cls":"Theorem","refnum":"??","title":"","neu":true,"id":"Theorem*-4.3","reftag":"","label":"Theorem","reflabel":"Theorem","autoid":"Theorem*-4.3","file":"lecture_10"},{"cls":"Definition","refnum":"??","title":"","neu":true,"id":"Definition*-5.1","reftag":"","label":"Definition","reflabel":"Definition","autoid":"Definition*-5.1","file":"lecture_10"},{"cls":"Proposition","refnum":"??","title":"","neu":true,"id":"Proposition*-5.2","reftag":"","label":"Proposition","reflabel":"Proposition","autoid":"Proposition*-5.2","file":"lecture_10"},{"cls":"Proposition","refnum":"??","title":"","neu":true,"id":"Proposition*-5.3","reftag":"","label":"Proposition","reflabel":"Proposition","autoid":"Proposition*-5.3","file":"lecture_10"},{"cls":"Definition","refnum":"??","title":"","neu":true,"id":"Definition*-7.1","reftag":"","label":"Definition","reflabel":"Definition","autoid":"Definition*-7.1","file":"lecture_10"},{"cls":"Proposition","refnum":"??","title":"","file":"lecture_10","id":"Proposition*-7.2","reftag":"","reflabel":"Proposition","autoid":"Proposition*-7.2","neu":true,"label":"Proposition"}]