[{"title":"","file":"lecture_3","autoid":"Theorem*-2.1","cls":"Theorem","reftag":"","reflabel":"Theorem","neu":true,"refnum":"??","id":"Theorem*-2.1","label":"Theorem"},{"title":"","file":"lecture_3","autoid":"Proof*-2.2","cls":"Proof","reftag":"","reflabel":"Proof","neu":true,"refnum":"??","id":"Proof*-2.2","label":"Proof"},{"title":"","file":"lecture_3","autoid":"Definition*-2.3","label":"Definition","reftag":"","reflabel":"Definition","neu":true,"refnum":"??","cls":"Definition","id":"Definition*-2.3"},{"title":"","file":"lecture_3","autoid":"Definition*-3.1","label":"Definition","reftag":"","reflabel":"Definition","neu":true,"refnum":"??","cls":"Definition","id":"Definition*-3.1"},{"title":"","file":"lecture_3","autoid":"Definition*-3.2","label":"Definition","reftag":"","reflabel":"Definition","neu":true,"refnum":"??","cls":"Definition","id":"Definition*-3.2"},{"title":"","file":"lecture_3","autoid":"Definition*-3.3","cls":"Definition","reftag":"","reflabel":"Definition","neu":true,"refnum":"??","id":"Definition*-3.3","label":"Definition"},{"title":"","file":"lecture_3","autoid":"Definition*-3.4","label":"Definition","reftag":"","reflabel":"Definition","neu":true,"refnum":"??","cls":"Definition","id":"Definition*-3.4"},{"title":"","file":"lecture_3","autoid":"Theorem*-3.5","label":"Theorem","reftag":"","reflabel":"Theorem","neu":true,"refnum":"??","cls":"Theorem","id":"Theorem*-3.5"},{"title":"","file":"lecture_3","autoid":"Definition*-3.6","cls":"Definition","reftag":"","reflabel":"Definition","neu":true,"refnum":"??","id":"Definition*-3.6","label":"Definition"},{"title":"","file":"lecture_3","autoid":"Definition*-3.7","cls":"Definition","reftag":"","reflabel":"Definition","neu":true,"refnum":"??","id":"Definition*-3.7","label":"Definition"},{"title":"","file":"lecture_3","autoid":"Definition*-3.8","label":"Definition","reftag":"","reflabel":"Definition","neu":true,"refnum":"??","cls":"Definition","id":"Definition*-3.8"},{"title":"","file":"lecture_3","autoid":"Definition*-3.9","cls":"Definition","reftag":"","reflabel":"Definition","neu":true,"refnum":"??","id":"Definition*-3.9","label":"Definition"},{"title":"","file":"lecture_3","autoid":"Theorem*-3.10","label":"Theorem","reftag":"","reflabel":"Theorem","neu":true,"refnum":"??","cls":"Theorem","id":"Theorem*-3.10"},{"title":"","file":"lecture_3","autoid":"Theorem*-3.11","cls":"Theorem","reftag":"","reflabel":"Theorem","neu":true,"refnum":"??","id":"Theorem*-3.11","label":"Theorem"},{"title":"","file":"lecture_3","autoid":"Theorem*-3.12","cls":"Theorem","reftag":"","reflabel":"Theorem","neu":true,"refnum":"??","id":"Theorem*-3.12","label":"Theorem"},{"title":"","file":"lecture_3","autoid":"Definition*-4.1","label":"Definition","reftag":"","reflabel":"Definition","neu":true,"refnum":"??","cls":"Definition","id":"Definition*-4.1"},{"title":"","file":"lecture_3","autoid":"Definition*-4.2","cls":"Definition","reftag":"","reflabel":"Definition","neu":true,"refnum":"??","id":"Definition*-4.2","label":"Definition"},{"title":"","file":"lecture_3","autoid":"Definition*-4.3","cls":"Definition","reftag":"","reflabel":"Definition","neu":true,"refnum":"??","id":"Definition*-4.3","label":"Definition"},{"title":"","file":"lecture_3","autoid":"Definition*-4.4","cls":"Definition","reftag":"","reflabel":"Definition","neu":true,"refnum":"??","id":"Definition*-4.4","label":"Definition"},{"title":"","file":"lecture_3","autoid":"Theorem*-4.5","cls":"Theorem","reftag":"","reflabel":"Theorem","neu":true,"refnum":"??","id":"Theorem*-4.5","label":"Theorem"},{"title":"","file":"lecture_3","autoid":"Definition*-5.1","cls":"Definition","reftag":"","reflabel":"Definition","neu":true,"refnum":"??","id":"Definition*-5.1","label":"Definition"},{"title":"","file":"lecture_3","autoid":"Theorem*-5.2","label":"Theorem","reftag":"","reflabel":"Theorem","neu":true,"refnum":"??","cls":"Theorem","id":"Theorem*-5.2"},{"title":"","file":"lecture_3","autoid":"Theorem*-5.3","cls":"Theorem","reftag":"","reflabel":"Theorem","neu":true,"refnum":"??","id":"Theorem*-5.3","label":"Theorem"},{"title":"","file":"lecture_3","autoid":"Theorem*-5.4","cls":"Theorem","reftag":"","reflabel":"Theorem","neu":true,"refnum":"??","id":"Theorem*-5.4","label":"Theorem"},{"title":"","file":"lecture_3","autoid":"Question*-6.1","cls":"Question","reftag":"","reflabel":"Question","neu":true,"refnum":"??","id":"Question*-6.1","label":"Question"},{"title":"","file":"lecture_3","autoid":"Definition*-6.2","cls":"Definition","reftag":"","reflabel":"Definition","neu":true,"refnum":"??","id":"Definition*-6.2","label":"Definition"},{"title":"","file":"lecture_3","autoid":"Theorem*-6.3","cls":"Theorem","reftag":"","reflabel":"Theorem","neu":true,"refnum":"??","id":"Theorem*-6.3","label":"Theorem"},{"title":"","file":"lecture_3","autoid":"Definition*-6.4","cls":"Definition","reftag":"","reflabel":"Definition","neu":true,"refnum":"??","id":"Definition*-6.4","label":"Definition"},{"title":"","file":"lecture_3","autoid":"Theorem*-6.5","cls":"Theorem","reftag":"","reflabel":"Theorem","neu":true,"refnum":"??","id":"Theorem*-6.5","label":"Theorem"},{"title":"","file":"lecture_3","autoid":"Theorem*-6.6","cls":"Theorem","reftag":"","reflabel":"Theorem","neu":true,"refnum":"??","id":"Theorem*-6.6","label":"Theorem"},{"title":"","file":"lecture_3","autoid":"Theorem*-6.7","cls":"Theorem","reftag":"","reflabel":"Theorem","neu":true,"refnum":"??","id":"Theorem*-6.7","label":"Theorem"},{"title":"","file":"lecture_3","autoid":"Definition*-7.1","label":"Definition","reftag":"","reflabel":"Definition","neu":true,"refnum":"??","cls":"Definition","id":"Definition*-7.1"},{"title":"","file":"lecture_3","autoid":"Definition*-7.2","label":"Definition","reftag":"","reflabel":"Definition","neu":true,"refnum":"??","cls":"Definition","id":"Definition*-7.2"},{"title":"","file":"lecture_3","autoid":"Definition*-7.3","cls":"Definition","reftag":"","reflabel":"Definition","neu":true,"refnum":"??","id":"Definition*-7.3","label":"Definition"},{"title":"","file":"lecture_3","autoid":"Definition*-7.4","cls":"Definition","reftag":"","reflabel":"Definition","neu":true,"refnum":"??","id":"Definition*-7.4","label":"Definition"},{"title":"","file":"lecture_3","autoid":"Definition*-7.5","cls":"Definition","reftag":"","reflabel":"Definition","neu":true,"refnum":"??","id":"Definition*-7.5","label":"Definition"},{"title":"","file":"lecture_3","autoid":"Definition*-7.6","cls":"Definition","reftag":"","reflabel":"Definition","neu":true,"refnum":"??","id":"Definition*-7.6","label":"Definition"},{"title":"","file":"lecture_3","autoid":"Definition*-7.7","cls":"Definition","reftag":"","reflabel":"Definition","neu":true,"refnum":"??","id":"Definition*-7.7","label":"Definition"},{"title":"","file":"lecture_3","autoid":"Definition*-7.8","cls":"Definition","reftag":"","reflabel":"Definition","neu":true,"refnum":"??","id":"Definition*-7.8","label":"Definition"},{"title":"","file":"lecture_3","autoid":"Definition*-7.9","cls":"Definition","reftag":"","reflabel":"Definition","neu":true,"refnum":"??","id":"Definition*-7.9","label":"Definition"},{"title":"","file":"lecture_3","autoid":"Theorem*-7.10","cls":"Theorem","reftag":"","reflabel":"Theorem","neu":true,"refnum":"??","id":"Theorem*-7.10","label":"Theorem"},{"title":"","file":"lecture_3","autoid":"Theorem*-7.11","cls":"Theorem","reftag":"","reflabel":"Theorem","neu":true,"refnum":"??","id":"Theorem*-7.11","label":"Theorem"},{"title":"","file":"lecture_3","autoid":"Theorem*-7.12","cls":"Theorem","reftag":"","reflabel":"Theorem","neu":true,"refnum":"??","id":"Theorem*-7.12","label":"Theorem"},{"title":"","file":"lecture_3","autoid":"Theorem*-7.13","cls":"Theorem","reftag":"","reflabel":"Theorem","neu":true,"refnum":"??","id":"Theorem*-7.13","label":"Theorem"},{"title":"","file":"lecture_3","autoid":"Theorem*-7.14","cls":"Theorem","reftag":"","reflabel":"Theorem","neu":true,"refnum":"??","id":"Theorem*-7.14","label":"Theorem"},{"title":"","file":"lecture_3","autoid":"Theorem*-7.15","cls":"Theorem","reftag":"","reflabel":"Theorem","neu":true,"refnum":"??","id":"Theorem*-7.15","label":"Theorem"},{"title":"","file":"lecture_3","autoid":"Theorem*-3.1","cls":"Theorem","reftag":"","reflabel":"Theorem","neu":true,"refnum":"??","id":"Theorem*-3.1","label":"Theorem"},{"title":"","file":"lecture_3","autoid":"Proof*-3.2","cls":"Proof","reftag":"","reflabel":"Proof","neu":true,"refnum":"??","id":"Proof*-3.2","label":"Proof"},{"title":"","file":"lecture_3","autoid":"Definition*-2.1","label":"Definition","reftag":"","reflabel":"Definition","neu":true,"refnum":"??","cls":"Definition","id":"Definition*-2.1"},{"title":"","file":"lecture_3","autoid":"Definition*-2.2","label":"Definition","reftag":"","reflabel":"Definition","neu":true,"refnum":"??","cls":"Definition","id":"Definition*-2.2"},{"title":"","file":"lecture_3","autoid":"Example*-2.4","cls":"Example","reftag":"","reflabel":"Example","neu":true,"refnum":"??","id":"Example*-2.4","label":"Example"},{"title":"","file":"lecture_3","autoid":"Theorem*-3.2","cls":"Theorem","reftag":"","reflabel":"Theorem","neu":true,"refnum":"??","id":"Theorem*-3.2","label":"Theorem"},{"title":"","file":"lecture_3","autoid":"Proof*-3.3","cls":"Proof","reftag":"","reflabel":"Proof","neu":true,"refnum":"??","id":"Proof*-3.3","label":"Proof"},{"title":"","file":"lecture_3","autoid":"Problem*-3.3","label":"Problem","reftag":"","reflabel":"Problem","neu":true,"refnum":"??","cls":"Problem","id":"Problem*-3.3"},{"title":"","file":"lecture_3","autoid":"Theorem*-3.4","cls":"Theorem","reftag":"","reflabel":"Theorem","neu":true,"refnum":"??","id":"Theorem*-3.4","label":"Theorem"},{"title":"","file":"lecture_3","autoid":"Proof*-3.5","cls":"Proof","reftag":"","reflabel":"Proof","neu":true,"refnum":"??","id":"Proof*-3.5","label":"Proof"},{"title":"","file":"lecture_3","autoid":"Proof*-3.6","cls":"Proof","reftag":"","reflabel":"Proof","neu":true,"refnum":"??","id":"Proof*-3.6","label":"Proof"},{"title":"","file":"lecture_3","autoid":"Theorem*-3.6","cls":"Theorem","reftag":"","reflabel":"Theorem","neu":true,"refnum":"??","id":"Theorem*-3.6","label":"Theorem"},{"title":"","file":"lecture_3","autoid":"Proof*-3.7","cls":"Proof","reftag":"","reflabel":"Proof","neu":true,"refnum":"??","id":"Proof*-3.7","label":"Proof"},{"title":"","file":"lecture_3","autoid":"Problem*-3.6","cls":"Problem","reftag":"","reflabel":"Problem","neu":true,"refnum":"??","id":"Problem*-3.6","label":"Problem"},{"title":"","file":"lecture_3","autoid":"Theorem*-3.7","cls":"Theorem","reftag":"","reflabel":"Theorem","neu":true,"refnum":"??","id":"Theorem*-3.7","label":"Theorem"},{"title":"","file":"lecture_3","autoid":"Proof*-3.8","cls":"Proof","reftag":"","reflabel":"Proof","neu":true,"refnum":"??","id":"Proof*-3.8","label":"Proof"},{"title":"","file":"lecture_3","autoid":"Proposition*-3.8","cls":"Proposition","reftag":"","reflabel":"Proposition","neu":true,"refnum":"??","id":"Proposition*-3.8","label":"Proposition"},{"title":"","file":"lecture_3","autoid":"Theorem*-3.9","cls":"Theorem","reftag":"","reflabel":"Theorem","neu":true,"refnum":"??","id":"Theorem*-3.9","label":"Theorem"},{"title":"","file":"lecture_3","autoid":"Proof*-3.11","cls":"Proof","reftag":"","reflabel":"Proof","neu":true,"refnum":"??","id":"Proof*-3.11","label":"Proof"},{"title":"","file":"lecture_3","autoid":"Lemma*-3.6","label":"Lemma","reftag":"","reflabel":"Lemma","neu":true,"refnum":"??","cls":"Lemma","id":"Lemma*-3.6"},{"title":"","file":"lecture_3","autoid":"Problem*-3.7","label":"Problem","reftag":"","reflabel":"Problem","neu":true,"refnum":"??","cls":"Problem","id":"Problem*-3.7"},{"title":"","file":"lecture_3","autoid":"Proposition*-3.9","label":"Proposition","reftag":"","reflabel":"Proposition","neu":true,"refnum":"??","cls":"Proposition","id":"Proposition*-3.9"},{"title":"","file":"lecture_3","autoid":"Proof*-3.12","cls":"Proof","reftag":"","reflabel":"Proof","neu":true,"refnum":"??","id":"Proof*-3.12","label":"Proof"},{"title":"","file":"lecture_3","autoid":"Theorem*-4.1","cls":"Theorem","reftag":"","reflabel":"Theorem","neu":true,"refnum":"??","id":"Theorem*-4.1","label":"Theorem"},{"title":"","file":"lecture_3","autoid":"Proof*-4.2","cls":"Proof","reftag":"","reflabel":"Proof","neu":true,"refnum":"??","id":"Proof*-4.2","label":"Proof"},{"title":"","file":"lecture_3","autoid":"Theorem*-4.2","label":"Theorem","reftag":"","reflabel":"Theorem","neu":true,"refnum":"??","cls":"Theorem","id":"Theorem*-4.2"},{"title":"","file":"lecture_3","autoid":"Theorem*-4.3","cls":"Theorem","reftag":"","reflabel":"Theorem","neu":true,"refnum":"??","id":"Theorem*-4.3","label":"Theorem"},{"title":"","file":"lecture_3","autoid":"Proof*-4.4","cls":"Proof","reftag":"","reflabel":"Proof","neu":true,"refnum":"??","id":"Proof*-4.4","label":"Proof"},{"title":"","file":"lecture_3","autoid":"Theorem*-5.1","cls":"Theorem","reftag":"","reflabel":"Theorem","neu":true,"refnum":"??","id":"Theorem*-5.1","label":"Theorem"},{"title":"","file":"lecture_3","autoid":"Proof*-5.2","cls":"Proof","reftag":"","reflabel":"Proof","neu":true,"refnum":"??","id":"Proof*-5.2","label":"Proof"},{"title":"","file":"lecture_3","autoid":"Question*-5.1","label":"Question","reftag":"","reflabel":"Question","neu":true,"refnum":"??","cls":"Question","id":"Question*-5.1"},{"title":"","file":"lecture_3","autoid":"Proof*-5.3","cls":"Proof","reftag":"","reflabel":"Proof","neu":true,"refnum":"??","id":"Proof*-5.3","label":"Proof"},{"title":"","file":"lecture_3","autoid":"Proof*-5.4","cls":"Proof","reftag":"","reflabel":"Proof","neu":true,"refnum":"??","id":"Proof*-5.4","label":"Proof"},{"title":"","file":"lecture_3","autoid":"Lemma*-5.3","label":"Lemma","reftag":"","reflabel":"Lemma","neu":true,"refnum":"??","cls":"Lemma","id":"Lemma*-5.3"},{"title":"","file":"lecture_3","autoid":"Proof*-5.5","cls":"Proof","reftag":"","reflabel":"Proof","neu":true,"refnum":"??","id":"Proof*-5.5","label":"Proof"},{"title":"","file":"lecture_3","autoid":"Theorem*-6.1","cls":"Theorem","reftag":"","reflabel":"Theorem","neu":true,"refnum":"??","id":"Theorem*-6.1","label":"Theorem"},{"title":"","file":"lecture_3","autoid":"Proof*-6.2","cls":"Proof","reftag":"","reflabel":"Proof","neu":true,"refnum":"??","id":"Proof*-6.2","label":"Proof"},{"title":"","file":"lecture_3","autoid":"Problem*-6.1","label":"Problem","reftag":"","reflabel":"Problem","neu":true,"refnum":"??","cls":"Problem","id":"Problem*-6.1"},{"title":"","file":"lecture_3","autoid":"Theorem*-6.2","cls":"Theorem","reftag":"","reflabel":"Theorem","neu":true,"refnum":"??","id":"Theorem*-6.2","label":"Theorem"},{"title":"","file":"lecture_3","autoid":"Proof*-6.3","cls":"Proof","reftag":"","reflabel":"Proof","neu":true,"refnum":"??","id":"Proof*-6.3","label":"Proof"},{"title":"","file":"lecture_3","autoid":"Question*-6.2","label":"Question","reftag":"","reflabel":"Question","neu":true,"refnum":"??","cls":"Question","id":"Question*-6.2"},{"title":"","file":"lecture_3","autoid":"Proof*-6.4","cls":"Proof","reftag":"","reflabel":"Proof","neu":true,"refnum":"??","id":"Proof*-6.4","label":"Proof"},{"title":"","file":"lecture_3","autoid":"Problem*-6.3","cls":"Problem","reftag":"","reflabel":"Problem","neu":true,"refnum":"??","id":"Problem*-6.3","label":"Problem"},{"title":"","file":"lecture_3","autoid":"Theorem*-6.4","cls":"Theorem","reftag":"","reflabel":"Theorem","neu":true,"refnum":"??","id":"Theorem*-6.4","label":"Theorem"},{"title":"","file":"lecture_3","autoid":"Proof*-6.5","cls":"Proof","reftag":"","reflabel":"Proof","neu":true,"refnum":"??","id":"Proof*-6.5","label":"Proof"},{"title":"","file":"lecture_3","autoid":"Question*-6.3","label":"Question","reftag":"","reflabel":"Question","neu":true,"refnum":"??","cls":"Question","id":"Question*-6.3"},{"title":"","file":"lecture_3","autoid":"Problem*-6.4","cls":"Problem","reftag":"","reflabel":"Problem","neu":true,"refnum":"??","id":"Problem*-6.4","label":"Problem"},{"title":"","file":"lecture_3","autoid":"Proof*-6.6","cls":"Proof","reftag":"","reflabel":"Proof","neu":true,"refnum":"??","id":"Proof*-6.6","label":"Proof"},{"title":"","file":"lecture_3","autoid":"Important*-6.4","label":"Important","reftag":"","reflabel":"Important","neu":true,"refnum":"??","cls":"Important","id":"Important*-6.4"},{"title":"","file":"lecture_3","autoid":"Problem*-6.5","label":"Problem","reftag":"","reflabel":"Problem","neu":true,"refnum":"??","cls":"Problem","id":"Problem*-6.5"},{"title":"","file":"lecture_3","autoid":"Problem*-6.6","cls":"Problem","reftag":"","reflabel":"Problem","neu":true,"refnum":"??","id":"Problem*-6.6","label":"Problem"},{"title":"","file":"lecture_3","autoid":"Question*-6.6","label":"Question","reftag":"","reflabel":"Question","neu":true,"refnum":"??","cls":"Question","id":"Question*-6.6"},{"title":"","file":"lecture_3","autoid":"Definition*-6.7","label":"Definition","reftag":"","reflabel":"Definition","neu":true,"refnum":"??","cls":"Definition","id":"Definition*-6.7"},{"title":"","file":"lecture_3","autoid":"Theorem*-6.8","label":"Theorem","reftag":"","reflabel":"Theorem","neu":true,"refnum":"??","cls":"Theorem","id":"Theorem*-6.8"},{"title":"Expectation and Variance of t distribution","file":"lecture_3","autoid":"Proposition*-6.9","cls":"Proposition","reftag":"","reflabel":"Proposition","neu":true,"refnum":"??","id":"expectation-and-variance-of-t-distribution","label":"Proposition"},{"title":"","file":"lecture_3","autoid":"Theorem*-6.9","label":"Theorem","reftag":"","reflabel":"Theorem","neu":true,"refnum":"??","cls":"Theorem","id":"Theorem*-6.9"},{"title":"Expectation and Variance of t-distribution","file":"lecture_3","autoid":"Proposition*-6.10","label":"Proposition","reftag":"","reflabel":"Proposition","neu":true,"refnum":"??","cls":"Proposition","id":"expectation-and-variance-of-t-distribution"}]